raindrop/__init__.py
raindrop/analytics.py
raindrop/interaction.py
raindrop/models.py
raindrop/redact.py
raindrop/version.py
raindrop/well-known-names.json
raindrop_ai-0.0.36.dist-info/METADATA
raindrop_ai-0.0.36.dist-info/WHEEL
raindrop_ai-0.0.36.dist-info/RECORD
