Metadata-Version: 2.1
Name: raindrop-ai
Version: 0.0.36
Summary: Raindrop AI (Python SDK)
License: MIT
Author: Raindrop AI
Author-email: sdk@raindrop.ai
Requires-Python: >=3.10, !=2.7.*, !=3.0.*, !=3.1.*, !=3.2.*, !=3.3.*, !=3.4.*, !=3.5.*, !=3.6.*, !=3.7.*, !=3.8.*, !=3.9.*
Classifier: License :: OSI Approved :: MIT License
Classifier: Programming Language :: Python :: 3
Classifier: Programming Language :: Python :: 3.10
Classifier: Programming Language :: Python :: 3.11
Classifier: Programming Language :: Python :: 3.12
Requires-Dist: opentelemetry-sdk (>=1.39.0)
Requires-Dist: pydantic (>=2.09,<3)
Requires-Dist: requests (>=2.32.3,<3.0.0)
Requires-Dist: traceloop-sdk (>=0.46.0)
Requires-Dist: urllib3 (>=2.6.0)
